README.txt
setup.cfg
setup.py
src/z3c/__init__.py
src/z3c.recipe.openoffice.egg-info/PKG-INFO
src/z3c.recipe.openoffice.egg-info/SOURCES.txt
src/z3c.recipe.openoffice.egg-info/dependency_links.txt
src/z3c.recipe.openoffice.egg-info/entry_points.txt
src/z3c.recipe.openoffice.egg-info/namespace_packages.txt
src/z3c.recipe.openoffice.egg-info/not-zip-safe
src/z3c.recipe.openoffice.egg-info/requires.txt
src/z3c.recipe.openoffice.egg-info/top_level.txt
src/z3c/recipe/__init__.py
src/z3c/recipe/openoffice/__init__.py
src/z3c/recipe/openoffice/recipe.py
