Metadata-Version: 1.0
Name: z3c.recipe.openoffice
Version: 0.2
Summary: zc.buildout recipe that downloads and installs OpenOffice.org
Home-page: http://svn.zope.org/z3c.recipe.openoffice
Author: Infrae
Author-email: faassen@infrae.com
License: ZPL 2.1
Keywords: buildout openoffice
Platform: UNKNOWN
